pydeepskylog/__init__.py
pydeepskylog/config.py
pydeepskylog/contrast_reserve.py
pydeepskylog/deepskylog_interface.py
pydeepskylog/exceptions.py
pydeepskylog/logging_config.py
pydeepskylog/magnitude.py
pydeepskylog/py.typed
pydeepskylog/sanitization.py
pydeepskylog/validation.py
pydeepskylog/version.py
pydeepskylog/tests/__init__.py
pydeepskylog/tests/test_config.py
pydeepskylog/tests/test_contrast_reserve.py
pydeepskylog/tests/test_deepskylog_interface.py
pydeepskylog/tests/test_exceptions.py
pydeepskylog/tests/test_logging.py
pydeepskylog/tests/test_magnitudes.py
pydeepskylog/tests/test_validation.py
pydeepskylog-1.6.dist-info/licenses/LICENSE
pydeepskylog-1.6.dist-info/METADATA
pydeepskylog-1.6.dist-info/WHEEL
pydeepskylog-1.6.dist-info/top_level.txt
pydeepskylog-1.6.dist-info/RECORD
